main.py
src/upload.py
src/utils/get_creds.py
src/utils/get_service.py
google_drive_uploader-0.1.0.dist-info/METADATA
google_drive_uploader-0.1.0.dist-info/WHEEL
google_drive_uploader-0.1.0.dist-info/RECORD
