Metadata-Version: 2.1
Name: google-drive-uploader
Version: 0.1.0
Summary: This is a simple file uploader to Google Drive
Author-email: Mai <mai@mai0313.com>
Requires-Python: >=3.8
Requires-Dist: google-api-python-client>=2.94.0
Requires-Dist: google-auth-oauthlib>=1.0.0
Requires-Dist: pydantic>=2.0.3
Requires-Dist: tqdm>=4.65.0
